observerutil/__init__.py
observerutil/interfaces.py
observerutil/observers.py
observerutil/parameter_adapters.py
observerutil-0.2.1.dist-info/METADATA
observerutil-0.2.1.dist-info/WHEEL
observerutil-0.2.1.dist-info/licenses/LICENSE
observerutil-0.2.1.dist-info/RECORD
