Metadata-Version: 2.4
Name: observerutil
Version: 0.2.1
Summary: Let you implement observer pattern from the box
Project-URL: Github repo, https://github.com/akvilary/observerutil
Project-URL: Bug tracker, https://github.com/akvilary/observerutil/issues
Author-email: Andrey Smirnov <smirnovcode@mail.ru>
License-File: LICENSE
Classifier: License :: CC0 1.0 Universal (CC0 1.0) Public Domain Dedication
Classifier: Operating System :: OS Independent
Classifier: Programming Language :: Python :: 3
Requires-Python: >=3.7
